watpy/__init__.py
watpy/coredb/__init__.py
watpy/coredb/coredb.py
watpy/coredb/metadata.py
watpy/utils/__init__.py
watpy/utils/coreh5.py
watpy/utils/ioutils.py
watpy/utils/num.py
watpy/utils/units.py
watpy/utils/viz.py
watpy/wave/__init__.py
watpy/wave/gwutils.py
watpy/wave/wave.py
core_watpy-0.1.1.dist-info/LICENSE
core_watpy-0.1.1.dist-info/METADATA
core_watpy-0.1.1.dist-info/WHEEL
core_watpy-0.1.1.dist-info/top_level.txt
core_watpy-0.1.1.dist-info/RECORD
