Metadata-Version: 2.1
Name: core-watpy
Version: 0.1.1
Summary: Waveform Analysis Tool in Python
Home-page: https://git.tpi.uni-jena.de/core/watpy
Author: CoRe Team
Author-email: The CoRe Team <core@listserv.uni-jena.de>
Project-URL: Homepage, https://git.tpi.uni-jena.de/core/watpy
Project-URL: Bug Tracker, https://git.tpi.uni-jena.de/core/watpy/-/issues
Project-URL: Mailing List, https://lserv.uni-jena.de/mailman/listinfo/core
Classifier: Programming Language :: Python :: 3
Classifier: License :: OSI Approved :: GNU General Public License v3 (GPLv3)
Classifier: Operating System :: OS Independent
Requires: h5py
Requires: numpy
Requires: matplotlib
Requires-Python: >=3.7
License-File: LICENSE
